mbcore/__init__.py
mbcore/_logging.py
mbcore/_traceback.py
mbcore/_typing.py
mbcore/cache.py
mbcore/collect.py
mbcore/deque.py
mbcore/display.py
mbcore/execute.py
mbcore/genstubs.py
mbcore/import_utils.py
mbcore/log.py
mbcore/more.py
mbcore/parse.py
mbcore/proto.py
mbcore/recipes.py
mbcore/resolve.py
mbcore/traverse.py
mbcore-0.1.3.dist-info/METADATA
mbcore-0.1.3.dist-info/WHEEL
mbcore-0.1.3.dist-info/entry_points.txt
mbcore-0.1.3.dist-info/top_level.txt
mbcore-0.1.3.dist-info/RECORD
