Metadata-Version: 2.2
Name: mbcore
Version: 0.1.3
Summary: Add your description here
Author-email: mbodiai team <info@mbodi.ai>
Requires-Python: >=3.10
Requires-Dist: rich-click>=1.8.5
Requires-Dist: rich
Provides-Extra: dev
Requires-Dist: pytest>=8.3.4; extra == "dev"
Requires-Dist: pytest-asyncio; extra == "dev"
